ldnlib/__init__.py
ldnlib/base.py
ldnlib/consumer.py
ldnlib/sender.py
py_ldnlib-0.1.3.dist-info/METADATA
py_ldnlib-0.1.3.dist-info/RECORD
py_ldnlib-0.1.3.dist-info/WHEEL
py_ldnlib-0.1.3.dist-info/top_level.txt
